README.md
dicetrust.py
setup.cfg
setup.py
dicetrust.egg-info/PKG-INFO
dicetrust.egg-info/SOURCES.txt
dicetrust.egg-info/dependency_links.txt
dicetrust.egg-info/entry_points.txt
dicetrust.egg-info/requires.txt
dicetrust.egg-info/top_level.txt
dicetrust.egg-info/zip-safe