Metadata-Version: 1.1
Name: dicetrust
Version: 0.1.1
Summary: DiceTrust API Client
Home-page: https://github.com/dicetrust/dicetrust.py
Author: Cenk Altı
Author-email: cenkalti@gmail.com
License: UNKNOWN
Platform: any
Classifier: License :: OSI Approved :: MIT License
Classifier: Programming Language :: Python :: 3.6
